<?xml version="1.0" encoding="UTF-8" standalone="yes"?>
<p:sld xmlns:a="http://schemas.openxmlformats.org/drawingml/2006/main" xmlns:r="http://schemas.openxmlformats.org/officeDocument/2006/relationships" xmlns:p="http://schemas.openxmlformats.org/presentationml/2006/main"><p:cSld><p:spTree><p:nvGrpSpPr><p:cNvPr id="1" name=""><a:extLst><a:ext uri="{FF2B5EF4-FFF2-40B4-BE49-F238E27FC236}"><a16:creationId xmlns:a16="http://schemas.microsoft.com/office/drawing/2014/main" id="{94A706E3-07E4-02F9-D6C3-DED205B2A88B}"/></a:ext></a:extLst></p:cNvPr><p:cNvGrpSpPr/><p:nvPr/></p:nvGrpSpPr><p:grpSpPr><a:xfrm><a:off x="0" y="0"/><a:ext cx="0" cy="0"/><a:chOff x="0" y="0"/><a:chExt cx="0" cy="0"/></a:xfrm></p:grpSpPr><p:sp><p:nvSpPr><p:cNvPr id="5" name="제목 4"><a:extLst><a:ext uri="{FF2B5EF4-FFF2-40B4-BE49-F238E27FC236}"><a16:creationId xmlns:a16="http://schemas.microsoft.com/office/drawing/2014/main" id="{920EF082-F0CA-752C-6806-1689F3916384}"/></a:ext></a:extLst></p:cNvPr><p:cNvSpPr><a:spLocks noGrp="1"/></p:cNvSpPr><p:nvPr><p:ph type="title"/></p:nvPr></p:nvSpPr><p:spPr/><p:txBody><a:bodyPr><a:noAutofit/></a:bodyPr><a:lstStyle/><a:p><a:pPr><a:lnSpc><a:spcPct val="150000"/></a:lnSpc><a:defRPr/></a:pPr><a:r><a:rPr lang="en-US" altLang="ko-KR" spc="-50" dirty="0"/><a:t>3.1 UI/UX </a:t></a:r><a:r><a:rPr lang="ko-KR" altLang="en-US" spc="-50" dirty="0"/><a:t>구현 방안</a:t></a:r><a:endParaRPr lang="en-US" altLang="ko-KR" spc="-50" dirty="0"><a:latin typeface="맑은 고딕" panose="020B0503020000020004" pitchFamily="50" charset="-127"/></a:endParaRPr></a:p></p:txBody></p:sp><p:sp><p:nvSpPr><p:cNvPr id="6" name="텍스트 개체 틀 5"><a:extLst><a:ext uri="{FF2B5EF4-FFF2-40B4-BE49-F238E27FC236}"><a16:creationId xmlns:a16="http://schemas.microsoft.com/office/drawing/2014/main" id="{F408FB11-FF2A-1D6B-814E-37975D231AB8}"/></a:ext></a:extLst></p:cNvPr><p:cNvSpPr><a:spLocks noGrp="1"/></p:cNvSpPr><p:nvPr><p:ph type="body" idx="1"/></p:nvPr></p:nvSpPr><p:spPr/><p:txBody><a:bodyPr><a:noAutofit/></a:bodyPr><a:lstStyle/><a:p><a:r><a:rPr lang="en-US" altLang="ko-KR" dirty="0"/><a:t>3. </a:t></a:r><a:r><a:rPr lang="ko-KR" altLang="en-US" dirty="0"/><a:t>요건 구현 방안</a:t></a:r></a:p></p:txBody></p:sp><p:grpSp><p:nvGrpSpPr><p:cNvPr id="29" name="그룹 28"><a:extLst><a:ext uri="{FF2B5EF4-FFF2-40B4-BE49-F238E27FC236}"><a16:creationId xmlns:a16="http://schemas.microsoft.com/office/drawing/2014/main" id="{17EC3E27-7D8B-C017-BAA6-44BB34608536}"/></a:ext></a:extLst></p:cNvPr><p:cNvGrpSpPr/><p:nvPr/></p:nvGrpSpPr><p:grpSpPr><a:xfrm><a:off x="213789" y="1008314"/><a:ext cx="9599752" cy="635602"/><a:chOff x="400759" y="1425246"/><a:chExt cx="9436394" cy="635602"/></a:xfrm></p:grpSpPr><p:sp><p:nvSpPr><p:cNvPr id="30" name="사각형: 위쪽 모서리의 한쪽은 둥글고 다른 한쪽은 잘림 29"><a:extLst><a:ext uri="{FF2B5EF4-FFF2-40B4-BE49-F238E27FC236}"><a16:creationId xmlns:a16="http://schemas.microsoft.com/office/drawing/2014/main" id="{D094359C-9AD2-5382-56C4-A519C6B0280C}"/></a:ext></a:extLst></p:cNvPr><p:cNvSpPr/><p:nvPr/></p:nvSpPr><p:spPr><a:xfrm><a:off x="400759" y="1441358"/><a:ext cx="662956" cy="184859"/></a:xfrm><a:prstGeom prst="snipRoundRect"><a:avLst/></a:prstGeom><a:solidFill><a:srgbClr val="123E8C"/></a:solidFill><a:ln><a:noFill/></a:ln></p:spPr><p:style><a:lnRef idx="2"><a:schemeClr val="accent1"><a:shade val="15000"/></a:schemeClr></a:lnRef><a:fillRef idx="1"><a:schemeClr val="accent1"/></a:fillRef><a:effectRef idx="0"><a:schemeClr val="accent1"/></a:effectRef><a:fontRef idx="minor"><a:schemeClr val="lt1"/></a:fontRef></p:style><p:txBody><a:bodyPr rtlCol="0" anchor="ctr"/><a:lstStyle/><a:p><a:pPr algn="ctr"/><a:endParaRPr lang="ko-KR" altLang="en-US" dirty="0"/></a:p></p:txBody></p:sp><p:sp><p:nvSpPr><p:cNvPr id="31" name="TextBox 30"><a:extLst><a:ext uri="{FF2B5EF4-FFF2-40B4-BE49-F238E27FC236}"><a16:creationId xmlns:a16="http://schemas.microsoft.com/office/drawing/2014/main" id="{464C64F5-E7B2-2E31-6742-CB23F8633432}"/></a:ext></a:extLst></p:cNvPr><p:cNvSpPr txBox="1"/><p:nvPr/></p:nvSpPr><p:spPr><a:xfrm><a:off x="446476" y="1425246"/><a:ext cx="552588" cy="200055"/></a:xfrm><a:prstGeom prst="rect"><a:avLst/></a:prstGeom><a:noFill/></p:spPr><p:txBody><a:bodyPr wrap="none" rtlCol="0"><a:spAutoFit/></a:bodyPr><a:lstStyle/><a:p><a:r><a:rPr lang="en-US" altLang="ko-KR" sz="700" dirty="0"><a:solidFill><a:srgbClr val="EFF5FF"/></a:solidFill><a:latin typeface="+mj-ea"/><a:ea typeface="+mj-ea"/></a:rPr><a:t>Summary</a:t></a:r><a:endParaRPr lang="ko-KR" altLang="en-US" sz="700" dirty="0"><a:solidFill><a:srgbClr val="EFF5FF"/></a:solidFill><a:latin typeface="+mj-ea"/><a:ea typeface="+mj-ea"/></a:endParaRPr></a:p></p:txBody></p:sp><p:sp><p:nvSpPr><p:cNvPr id="32" name="직사각형 31"><a:extLst><a:ext uri="{FF2B5EF4-FFF2-40B4-BE49-F238E27FC236}"><a16:creationId xmlns:a16="http://schemas.microsoft.com/office/drawing/2014/main" id="{75D66A3B-DFB0-2AED-E298-1CF20D725240}"/></a:ext></a:extLst></p:cNvPr><p:cNvSpPr/><p:nvPr/></p:nvSpPr><p:spPr><a:xfrm><a:off x="400759" y="1612761"/><a:ext cx="45719" cy="448087"/></a:xfrm><a:prstGeom prst="rect"><a:avLst/></a:prstGeom><a:solidFill><a:srgbClr val="123E8C"/></a:solidFill><a:ln><a:noFill/></a:ln></p:spPr><p:style><a:lnRef idx="2"><a:schemeClr val="accent1"><a:shade val="15000"/></a:schemeClr></a:lnRef><a:fillRef idx="1"><a:schemeClr val="accent1"/></a:fillRef><a:effectRef idx="0"><a:schemeClr val="accent1"/></a:effectRef><a:fontRef idx="minor"><a:schemeClr val="lt1"/></a:fontRef></p:style><p:txBody><a:bodyPr rtlCol="0" anchor="ctr"/><a:lstStyle/><a:p><a:pPr algn="ctr"/><a:endParaRPr lang="ko-KR" altLang="en-US" dirty="0"/></a:p></p:txBody></p:sp><p:sp><p:nvSpPr><p:cNvPr id="33" name="직사각형 32"><a:extLst><a:ext uri="{FF2B5EF4-FFF2-40B4-BE49-F238E27FC236}"><a16:creationId xmlns:a16="http://schemas.microsoft.com/office/drawing/2014/main" id="{E6947345-DFF8-784E-91F7-CC8C2B7FB9F9}"/></a:ext></a:extLst></p:cNvPr><p:cNvSpPr/><p:nvPr/></p:nvSpPr><p:spPr><a:xfrm><a:off x="9791433" y="1612761"/><a:ext cx="45719" cy="448087"/></a:xfrm><a:prstGeom prst="rect"><a:avLst/></a:prstGeom><a:solidFill><a:srgbClr val="123E8C"/></a:solidFill><a:ln><a:noFill/></a:ln></p:spPr><p:style><a:lnRef idx="2"><a:schemeClr val="accent1"><a:shade val="15000"/></a:schemeClr></a:lnRef><a:fillRef idx="1"><a:schemeClr val="accent1"/></a:fillRef><a:effectRef idx="0"><a:schemeClr val="accent1"/></a:effectRef><a:fontRef idx="minor"><a:schemeClr val="lt1"/></a:fontRef></p:style><p:txBody><a:bodyPr rtlCol="0" anchor="ctr"/><a:lstStyle/><a:p><a:pPr algn="ctr"/><a:endParaRPr lang="ko-KR" altLang="en-US" dirty="0"/></a:p></p:txBody></p:sp><p:sp><p:nvSpPr><p:cNvPr id="34" name="직사각형 33"><a:extLst><a:ext uri="{FF2B5EF4-FFF2-40B4-BE49-F238E27FC236}"><a16:creationId xmlns:a16="http://schemas.microsoft.com/office/drawing/2014/main" id="{4452D8EE-7BFC-0093-4609-FC1DBBA82D76}"/></a:ext></a:extLst></p:cNvPr><p:cNvSpPr/><p:nvPr/></p:nvSpPr><p:spPr><a:xfrm rot="16200000"><a:off x="5118956" y="-3091031"/><a:ext cx="45719" cy="9390675"/></a:xfrm><a:prstGeom prst="rect"><a:avLst/></a:prstGeom><a:solidFill><a:srgbClr val="123E8C"/></a:solidFill><a:ln><a:noFill/></a:ln></p:spPr><p:style><a:lnRef idx="2"><a:schemeClr val="accent1"><a:shade val="15000"/></a:schemeClr></a:lnRef><a:fillRef idx="1"><a:schemeClr val="accent1"/></a:fillRef><a:effectRef idx="0"><a:schemeClr val="accent1"/></a:effectRef><a:fontRef idx="minor"><a:schemeClr val="lt1"/></a:fontRef></p:style><p:txBody><a:bodyPr rtlCol="0" anchor="ctr"/><a:lstStyle/><a:p><a:pPr algn="ctr"/><a:endParaRPr lang="ko-KR" altLang="en-US" dirty="0"/></a:p></p:txBody></p:sp></p:grpSp><p:sp><p:nvSpPr><p:cNvPr id="35" name="TextBox 34"><a:extLst><a:ext uri="{FF2B5EF4-FFF2-40B4-BE49-F238E27FC236}"><a16:creationId xmlns:a16="http://schemas.microsoft.com/office/drawing/2014/main" id="{633B87F1-1DC6-E9B0-73CF-DBD4949A0A96}"/></a:ext></a:extLst></p:cNvPr><p:cNvSpPr txBox="1"/><p:nvPr/></p:nvSpPr><p:spPr><a:xfrm><a:off x="333748" y="620688"/><a:ext cx="3467123" cy="333617"/></a:xfrm><a:prstGeom prst="rect"><a:avLst/></a:prstGeom><a:noFill/></p:spPr><p:txBody><a:bodyPr wrap="square"><a:spAutoFit/></a:bodyPr><a:lstStyle/><a:p><a:pPr><a:lnSpc><a:spcPct val="150000"/></a:lnSpc><a:defRPr/></a:pPr><a:r><a:rPr lang="ko-KR" altLang="en-US" sz="1200" spc="-50" dirty="0"><a:latin typeface="+mj-ea"/></a:rPr><a:t>세부 구현방안 </a:t></a:r><a:r><a:rPr lang="en-US" altLang="ko-KR" sz="1200" spc="-50" dirty="0"><a:latin typeface="+mj-ea"/><a:ea typeface="+mj-ea"/></a:rPr><a:t>&gt; </a:t></a:r><a:r><a:rPr lang="ko-KR" altLang="en-US" sz="1200" b="1" spc="-50" dirty="0"><a:latin typeface="+mj-ea"/><a:ea typeface="+mj-ea"/></a:rPr><a:t>사용자 중심 쇼핑 </a:t></a:r><a:r><a:rPr lang="en-US" altLang="ko-KR" sz="1200" b="1" spc="-50" dirty="0"><a:latin typeface="+mj-ea"/><a:ea typeface="+mj-ea"/></a:rPr><a:t>UI </a:t></a:r><a:r><a:rPr lang="ko-KR" altLang="en-US" sz="1200" b="1" spc="-50" dirty="0"><a:latin typeface="+mj-ea"/><a:ea typeface="+mj-ea"/></a:rPr><a:t>구현</a:t></a:r><a:r><a:rPr lang="en-US" altLang="ko-KR" sz="1200" b="1" spc="-50" dirty="0"><a:latin typeface="+mj-ea"/><a:ea typeface="+mj-ea"/></a:rPr><a:t>(2/2)</a:t></a:r><a:endParaRPr lang="ko-KR" altLang="en-US" sz="1200" b="1" spc="-50" dirty="0"><a:solidFill><a:srgbClr val="D11726"/></a:solidFill><a:latin typeface="+mj-ea"/><a:ea typeface="+mj-ea"/></a:endParaRPr></a:p></p:txBody></p:sp><p:grpSp><p:nvGrpSpPr><p:cNvPr id="2" name="그룹 1"><a:extLst><a:ext uri="{FF2B5EF4-FFF2-40B4-BE49-F238E27FC236}"><a16:creationId xmlns:a16="http://schemas.microsoft.com/office/drawing/2014/main" id="{D9AC549E-2D14-5735-64AB-5B993ACFB52F}"/></a:ext></a:extLst></p:cNvPr><p:cNvGrpSpPr/><p:nvPr/></p:nvGrpSpPr><p:grpSpPr><a:xfrm><a:off x="200474" y="739123"/><a:ext cx="157894" cy="150700"/><a:chOff x="92460" y="548680"/><a:chExt cx="347360" cy="307222"/></a:xfrm></p:grpSpPr><p:sp><p:nvSpPr><p:cNvPr id="7" name="직사각형 6"><a:extLst><a:ext uri="{FF2B5EF4-FFF2-40B4-BE49-F238E27FC236}"><a16:creationId xmlns:a16="http://schemas.microsoft.com/office/drawing/2014/main" id="{70A95BF4-0FC8-159D-82B4-15B7AF195B90}"/></a:ext></a:extLst></p:cNvPr><p:cNvSpPr/><p:nvPr/></p:nvSpPr><p:spPr><a:xfrm><a:off x="218500" y="634581"/><a:ext cx="221320" cy="221321"/></a:xfrm><a:prstGeom prst="rect"><a:avLst/></a:prstGeom><a:solidFill><a:srgbClr val="DC2F34"/></a:solidFill><a:ln><a:noFill/></a:ln></p:spPr><p:style><a:lnRef idx="2"><a:schemeClr val="accent1"><a:shade val="15000"/></a:schemeClr></a:lnRef><a:fillRef idx="1"><a:schemeClr val="accent1"/></a:fillRef><a:effectRef idx="0"><a:schemeClr val="accent1"/></a:effectRef><a:fontRef idx="minor"><a:schemeClr val="lt1"/></a:fontRef></p:style><p:txBody><a:bodyPr rtlCol="0" anchor="ctr"/><a:lstStyle/><a:p><a:pPr algn="ctr"/><a:endParaRPr lang="ko-KR" altLang="en-US" dirty="0"><a:ea typeface="맑은 고딕" panose="020B0503020000020004" pitchFamily="50" charset="-127"/></a:endParaRPr></a:p></p:txBody></p:sp><p:sp><p:nvSpPr><p:cNvPr id="8" name="직사각형 7"><a:extLst><a:ext uri="{FF2B5EF4-FFF2-40B4-BE49-F238E27FC236}"><a16:creationId xmlns:a16="http://schemas.microsoft.com/office/drawing/2014/main" id="{480E3C62-AA17-D76C-8FB2-4C125AFD9015}"/></a:ext></a:extLst></p:cNvPr><p:cNvSpPr/><p:nvPr/></p:nvSpPr><p:spPr><a:xfrm><a:off x="164468" y="603978"/><a:ext cx="221321" cy="196730"/></a:xfrm><a:prstGeom prst="rect"><a:avLst/></a:prstGeom><a:solidFill><a:srgbClr val="123E8C"/></a:solidFill><a:ln><a:noFill/></a:ln></p:spPr><p:style><a:lnRef idx="2"><a:schemeClr val="accent1"><a:shade val="15000"/></a:schemeClr></a:lnRef><a:fillRef idx="1"><a:schemeClr val="accent1"/></a:fillRef><a:effectRef idx="0"><a:schemeClr val="accent1"/></a:effectRef><a:fontRef idx="minor"><a:schemeClr val="lt1"/></a:fontRef></p:style><p:txBody><a:bodyPr rtlCol="0" anchor="ctr"/><a:lstStyle/><a:p><a:pPr algn="ctr"/><a:endParaRPr lang="ko-KR" altLang="en-US" dirty="0"><a:ea typeface="맑은 고딕" panose="020B0503020000020004" pitchFamily="50" charset="-127"/></a:endParaRPr></a:p></p:txBody></p:sp><p:sp><p:nvSpPr><p:cNvPr id="9" name="직사각형 8"><a:extLst><a:ext uri="{FF2B5EF4-FFF2-40B4-BE49-F238E27FC236}"><a16:creationId xmlns:a16="http://schemas.microsoft.com/office/drawing/2014/main" id="{FC5C2429-B35C-0675-925E-C95C5E07C4DA}"/></a:ext></a:extLst></p:cNvPr><p:cNvSpPr/><p:nvPr/></p:nvSpPr><p:spPr><a:xfrm><a:off x="92460" y="548680"/><a:ext cx="229950" cy="198228"/></a:xfrm><a:prstGeom prst="rect"><a:avLst/></a:prstGeom><a:solidFill><a:srgbClr val="F5E428"/></a:solidFill><a:ln><a:noFill/></a:ln></p:spPr><p:style><a:lnRef idx="2"><a:schemeClr val="accent1"><a:shade val="15000"/></a:schemeClr></a:lnRef><a:fillRef idx="1"><a:schemeClr val="accent1"/></a:fillRef><a:effectRef idx="0"><a:schemeClr val="accent1"/></a:effectRef><a:fontRef idx="minor"><a:schemeClr val="lt1"/></a:fontRef></p:style><p:txBody><a:bodyPr rtlCol="0" anchor="ctr"/><a:lstStyle/><a:p><a:pPr algn="ctr"/><a:endParaRPr lang="ko-KR" altLang="en-US" dirty="0"><a:ea typeface="맑은 고딕" panose="020B0503020000020004" pitchFamily="50" charset="-127"/></a:endParaRPr></a:p></p:txBody></p:sp></p:grpSp><p:sp><p:nvSpPr><p:cNvPr id="56" name="TextBox 55"><a:extLst><a:ext uri="{FF2B5EF4-FFF2-40B4-BE49-F238E27FC236}"><a16:creationId xmlns:a16="http://schemas.microsoft.com/office/drawing/2014/main" id="{5B716FB1-1385-9F03-778E-86FBFD61A2AF}"/></a:ext></a:extLst></p:cNvPr><p:cNvSpPr txBox="1"/><p:nvPr/></p:nvSpPr><p:spPr><a:xfrm><a:off x="524508" y="1891861"/><a:ext cx="1244251" cy="276999"/></a:xfrm><a:prstGeom prst="rect"><a:avLst/></a:prstGeom><a:noFill/></p:spPr><p:txBody><a:bodyPr wrap="none" rtlCol="0"><a:spAutoFit/></a:bodyPr><a:lstStyle/><a:p><a:r><a:rPr kumimoji="1" lang="ko-KR" altLang="en-US" sz="1200" spc="-150" dirty="0"><a:solidFill><a:srgbClr val="DC2F34"/></a:solidFill><a:latin typeface="+mn-ea"/></a:rPr><a:t>대표 화면 </a:t></a:r><a:r><a:rPr kumimoji="1" lang="en-US" altLang="ko-KR" sz="1200" spc="-150" dirty="0"><a:solidFill><a:srgbClr val="DC2F34"/></a:solidFill><a:latin typeface="+mn-ea"/></a:rPr><a:t>UI </a:t></a:r><a:r><a:rPr kumimoji="1" lang="ko-KR" altLang="en-US" sz="1200" spc="-150" dirty="0"><a:solidFill><a:srgbClr val="DC2F34"/></a:solidFill><a:latin typeface="+mn-ea"/></a:rPr><a:t>구조</a:t></a:r><a:r><a:rPr kumimoji="1" lang="en-US" altLang="ko-KR" sz="1200" spc="-150" dirty="0"><a:solidFill><a:srgbClr val="DC2F34"/></a:solidFill><a:latin typeface="+mn-ea"/></a:rPr><a:t> </a:t></a:r><a:endParaRPr kumimoji="1" lang="ko-KR" altLang="en-US" sz="1200" spc="-150" dirty="0"><a:solidFill><a:srgbClr val="DC2F34"/></a:solidFill><a:latin typeface="+mn-ea"/></a:endParaRPr></a:p></p:txBody></p:sp><p:grpSp><p:nvGrpSpPr><p:cNvPr id="57" name="Check"><a:extLst><a:ext uri="{FF2B5EF4-FFF2-40B4-BE49-F238E27FC236}"><a16:creationId xmlns:a16="http://schemas.microsoft.com/office/drawing/2014/main" id="{AA5286A7-7AA3-AD3E-9509-C17280A4ECFB}"/></a:ext></a:extLst></p:cNvPr><p:cNvGrpSpPr><a:grpSpLocks noChangeAspect="1"/></p:cNvGrpSpPr><p:nvPr/></p:nvGrpSpPr><p:grpSpPr><a:xfrm><a:off x="344488" y="1927865"/><a:ext cx="193405" cy="193405"/><a:chOff x="2717799" y="1408113"/><a:chExt cx="377825" cy="377825"/></a:xfrm><a:solidFill><a:srgbClr val="C00000"/></a:solidFill></p:grpSpPr><p:sp><p:nvSpPr><p:cNvPr id="58" name="Check Icon"><a:extLst><a:ext uri="{FF2B5EF4-FFF2-40B4-BE49-F238E27FC236}"><a16:creationId xmlns:a16="http://schemas.microsoft.com/office/drawing/2014/main" id="{BCF86D8C-CD25-737B-0379-0E2C917E728C}"/></a:ext></a:extLst></p:cNvPr><p:cNvSpPr><a:spLocks noChangeAspect="1"/></p:cNvSpPr><p:nvPr/></p:nvSpPr><p:spPr bwMode="auto"><a:xfrm><a:off x="2809874" y="1516856"/><a:ext cx="193675" cy="160338"/></a:xfrm><a:custGeom><a:avLst/><a:gdLst><a:gd name="T0" fmla="*/ 15 w 122"/><a:gd name="T1" fmla="*/ 35 h 101"/><a:gd name="T2" fmla="*/ 51 w 122"/><a:gd name="T3" fmla="*/ 71 h 101"/><a:gd name="T4" fmla="*/ 107 w 122"/><a:gd name="T5" fmla="*/ 0 h 101"/><a:gd name="T6" fmla="*/ 122 w 122"/><a:gd name="T7" fmla="*/ 15 h 101"/><a:gd name="T8" fmla="*/ 51 w 122"/><a:gd name="T9" fmla="*/ 101 h 101"/><a:gd name="T10" fmla="*/ 0 w 122"/><a:gd name="T11" fmla="*/ 51 h 101"/><a:gd name="T12" fmla="*/ 15 w 122"/><a:gd name="T13" fmla="*/ 35 h 101"/></a:gdLst><a:ahLst/><a:cxnLst><a:cxn ang="0"><a:pos x="T0" y="T1"/></a:cxn><a:cxn ang="0"><a:pos x="T2" y="T3"/></a:cxn><a:cxn ang="0"><a:pos x="T4" y="T5"/></a:cxn><a:cxn ang="0"><a:pos x="T6" y="T7"/></a:cxn><a:cxn ang="0"><a:pos x="T8" y="T9"/></a:cxn><a:cxn ang="0"><a:pos x="T10" y="T11"/></a:cxn><a:cxn ang="0"><a:pos x="T12" y="T13"/></a:cxn></a:cxnLst><a:rect l="0" t="0" r="r" b="b"/><a:pathLst><a:path w="122" h="101"><a:moveTo><a:pt x="15" y="35"/></a:moveTo><a:lnTo><a:pt x="51" y="71"/></a:lnTo><a:lnTo><a:pt x="107" y="0"/></a:lnTo><a:lnTo><a:pt x="122" y="15"/></a:lnTo><a:lnTo><a:pt x="51" y="101"/></a:lnTo><a:lnTo><a:pt x="0" y="51"/></a:lnTo><a:lnTo><a:pt x="15" y="35"/></a:lnTo><a:close/></a:path></a:pathLst></a:custGeom><a:grpFill/><a:ln w="9525"><a:noFill/><a:round/><a:headEnd/><a:tailEnd/></a:ln></p:spPr><p:txBody><a:bodyPr vert="horz" wrap="square" lIns="91440" tIns="45720" rIns="91440" bIns="45720" numCol="1" anchor="t" anchorCtr="0" compatLnSpc="1"><a:prstTxWarp prst="textNoShape"><a:avLst/></a:prstTxWarp></a:bodyPr><a:lstStyle><a:defPPr><a:defRPr lang="en-US"/></a:defPPr><a:lvl1pPr marL="0" algn="l" defTabSz="914400" rtl="0" eaLnBrk="1" latinLnBrk="0" hangingPunct="1"><a:defRPr sz="1800" kern="1200"><a:solidFill><a:schemeClr val="tx1"/></a:solidFill><a:latin typeface="+mn-lt"/><a:ea typeface="+mn-ea"/><a:cs typeface="+mn-cs"/></a:defRPr></a:lvl1pPr><a:lvl2pPr marL="457200" algn="l" defTabSz="914400" rtl="0" eaLnBrk="1" latinLnBrk="0" hangingPunct="1"><a:defRPr sz="1800" kern="1200"><a:solidFill><a:schemeClr val="tx1"/></a:solidFill><a:latin typeface="+mn-lt"/><a:ea typeface="+mn-ea"/><a:cs typeface="+mn-cs"/></a:defRPr></a:lvl2pPr><a:lvl3pPr marL="914400" algn="l" defTabSz="914400" rtl="0" eaLnBrk="1" latinLnBrk="0" hangingPunct="1"><a:defRPr sz="1800" kern="1200"><a:solidFill><a:schemeClr val="tx1"/></a:solidFill><a:latin typeface="+mn-lt"/><a:ea typeface="+mn-ea"/><a:cs typeface="+mn-cs"/></a:defRPr></a:lvl3pPr><a:lvl4pPr marL="1371600" algn="l" defTabSz="914400" rtl="0" eaLnBrk="1" latinLnBrk="0" hangingPunct="1"><a:defRPr sz="1800" kern="1200"><a:solidFill><a:schemeClr val="tx1"/></a:solidFill><a:latin typeface="+mn-lt"/><a:ea typeface="+mn-ea"/><a:cs typeface="+mn-cs"/></a:defRPr></a:lvl4pPr><a:lvl5pPr marL="1828800" algn="l" defTabSz="914400" rtl="0" eaLnBrk="1" latinLnBrk="0" hangingPunct="1"><a:defRPr sz="1800" kern="1200"><a:solidFill><a:schemeClr val="tx1"/></a:solidFill><a:latin typeface="+mn-lt"/><a:ea typeface="+mn-ea"/><a:cs typeface="+mn-cs"/></a:defRPr></a:lvl5pPr><a:lvl6pPr marL="2286000" algn="l" defTabSz="914400" rtl="0" eaLnBrk="1" latinLnBrk="0" hangingPunct="1"><a:defRPr sz="1800" kern="1200"><a:solidFill><a:schemeClr val="tx1"/></a:solidFill><a:latin typeface="+mn-lt"/><a:ea typeface="+mn-ea"/><a:cs typeface="+mn-cs"/></a:defRPr></a:lvl6pPr><a:lvl7pPr marL="2743200" algn="l" defTabSz="914400" rtl="0" eaLnBrk="1" latinLnBrk="0" hangingPunct="1"><a:defRPr sz="1800" kern="1200"><a:solidFill><a:schemeClr val="tx1"/></a:solidFill><a:latin typeface="+mn-lt"/><a:ea typeface="+mn-ea"/><a:cs typeface="+mn-cs"/></a:defRPr></a:lvl7pPr><a:lvl8pPr marL="3200400" algn="l" defTabSz="914400" rtl="0" eaLnBrk="1" latinLnBrk="0" hangingPunct="1"><a:defRPr sz="1800" kern="1200"><a:solidFill><a:schemeClr val="tx1"/></a:solidFill><a:latin typeface="+mn-lt"/><a:ea typeface="+mn-ea"/><a:cs typeface="+mn-cs"/></a:defRPr></a:lvl8pPr><a:lvl9pPr marL="3657600" algn="l" defTabSz="914400" rtl="0" eaLnBrk="1" latinLnBrk="0" hangingPunct="1"><a:defRPr sz="1800" kern="1200"><a:solidFill><a:schemeClr val="tx1"/></a:solidFill><a:latin typeface="+mn-lt"/><a:ea typeface="+mn-ea"/><a:cs typeface="+mn-cs"/></a:defRPr></a:lvl9pPr></a:lstStyle><a:p><a:pPr algn="ctr"/><a:endParaRPr lang="en-US" sz="900"><a:solidFill><a:srgbClr val="DC2F34"/></a:solidFill><a:latin typeface="돋움" pitchFamily="50" charset="-127"/><a:ea typeface="돋움" pitchFamily="50" charset="-127"/></a:endParaRPr></a:p></p:txBody></p:sp><p:sp><p:nvSpPr><p:cNvPr id="59" name="Circle"><a:extLst><a:ext uri="{FF2B5EF4-FFF2-40B4-BE49-F238E27FC236}"><a16:creationId xmlns:a16="http://schemas.microsoft.com/office/drawing/2014/main" id="{8759A452-CC16-B3C0-4742-13AA1B54D2E7}"/></a:ext></a:extLst></p:cNvPr><p:cNvSpPr><a:spLocks noChangeAspect="1" noEditPoints="1"/></p:cNvSpPr><p:nvPr/></p:nvSpPr><p:spPr bwMode="auto"><a:xfrm><a:off x="2717799" y="1408113"/><a:ext cx="377825" cy="377825"/></a:xfrm><a:custGeom><a:avLst/><a:gdLst><a:gd name="T0" fmla="*/ 663 w 1327"/><a:gd name="T1" fmla="*/ 0 h 1326"/><a:gd name="T2" fmla="*/ 1327 w 1327"/><a:gd name="T3" fmla="*/ 663 h 1326"/><a:gd name="T4" fmla="*/ 663 w 1327"/><a:gd name="T5" fmla="*/ 1326 h 1326"/><a:gd name="T6" fmla="*/ 0 w 1327"/><a:gd name="T7" fmla="*/ 663 h 1326"/><a:gd name="T8" fmla="*/ 663 w 1327"/><a:gd name="T9" fmla="*/ 0 h 1326"/><a:gd name="T10" fmla="*/ 663 w 1327"/><a:gd name="T11" fmla="*/ 85 h 1326"/><a:gd name="T12" fmla="*/ 85 w 1327"/><a:gd name="T13" fmla="*/ 663 h 1326"/><a:gd name="T14" fmla="*/ 663 w 1327"/><a:gd name="T15" fmla="*/ 1242 h 1326"/><a:gd name="T16" fmla="*/ 1242 w 1327"/><a:gd name="T17" fmla="*/ 663 h 1326"/><a:gd name="T18" fmla="*/ 663 w 1327"/><a:gd name="T19" fmla="*/ 85 h 1326"/></a:gdLst><a:ahLst/><a:cxnLst><a:cxn ang="0"><a:pos x="T0" y="T1"/></a:cxn><a:cxn ang="0"><a:pos x="T2" y="T3"/></a:cxn><a:cxn ang="0"><a:pos x="T4" y="T5"/></a:cxn><a:cxn ang="0"><a:pos x="T6" y="T7"/></a:cxn><a:cxn ang="0"><a:pos x="T8" y="T9"/></a:cxn><a:cxn ang="0"><a:pos x="T10" y="T11"/></a:cxn><a:cxn ang="0"><a:pos x="T12" y="T13"/></a:cxn><a:cxn ang="0"><a:pos x="T14" y="T15"/></a:cxn><a:cxn ang="0"><a:pos x="T16" y="T17"/></a:cxn><a:cxn ang="0"><a:pos x="T18" y="T19"/></a:cxn></a:cxnLst><a:rect l="0" t="0" r="r" b="b"/><a:pathLst><a:path w="1327" h="1326"><a:moveTo><a:pt x="663" y="0"/></a:moveTo><a:cubicBezTo><a:pt x="1030" y="0"/><a:pt x="1327" y="297"/><a:pt x="1327" y="663"/></a:cubicBezTo><a:cubicBezTo><a:pt x="1327" y="1029"/><a:pt x="1030" y="1326"/><a:pt x="663" y="1326"/></a:cubicBezTo><a:cubicBezTo><a:pt x="297" y="1326"/><a:pt x="0" y="1029"/><a:pt x="0" y="663"/></a:cubicBezTo><a:cubicBezTo><a:pt x="0" y="297"/><a:pt x="297" y="0"/><a:pt x="663" y="0"/></a:cubicBezTo><a:close/><a:moveTo><a:pt x="663" y="85"/></a:moveTo><a:cubicBezTo><a:pt x="344" y="85"/><a:pt x="85" y="344"/><a:pt x="85" y="663"/></a:cubicBezTo><a:cubicBezTo><a:pt x="85" y="983"/><a:pt x="344" y="1242"/><a:pt x="663" y="1242"/></a:cubicBezTo><a:cubicBezTo><a:pt x="983" y="1242"/><a:pt x="1242" y="983"/><a:pt x="1242" y="663"/></a:cubicBezTo><a:cubicBezTo><a:pt x="1242" y="344"/><a:pt x="983" y="85"/><a:pt x="663" y="85"/></a:cubicBezTo><a:close/></a:path></a:pathLst></a:custGeom><a:grpFill/><a:ln w="0"><a:noFill/><a:prstDash val="solid"/><a:round/><a:headEnd/><a:tailEnd/></a:ln></p:spPr><p:txBody><a:bodyPr vert="horz" wrap="square" lIns="91440" tIns="45720" rIns="91440" bIns="45720" numCol="1" anchor="t" anchorCtr="0" compatLnSpc="1"><a:prstTxWarp prst="textNoShape"><a:avLst/></a:prstTxWarp></a:bodyPr><a:lstStyle><a:defPPr><a:defRPr lang="en-US"/></a:defPPr><a:lvl1pPr marL="0" algn="l" defTabSz="914400" rtl="0" eaLnBrk="1" latinLnBrk="0" hangingPunct="1"><a:defRPr sz="1800" kern="1200"><a:solidFill><a:schemeClr val="tx1"/></a:solidFill><a:latin typeface="+mn-lt"/><a:ea typeface="+mn-ea"/><a:cs typeface="+mn-cs"/></a:defRPr></a:lvl1pPr><a:lvl2pPr marL="457200" algn="l" defTabSz="914400" rtl="0" eaLnBrk="1" latinLnBrk="0" hangingPunct="1"><a:defRPr sz="1800" kern="1200"><a:solidFill><a:schemeClr val="tx1"/></a:solidFill><a:latin typeface="+mn-lt"/><a:ea typeface="+mn-ea"/><a:cs typeface="+mn-cs"/></a:defRPr></a:lvl2pPr><a:lvl3pPr marL="914400" algn="l" defTabSz="914400" rtl="0" eaLnBrk="1" latinLnBrk="0" hangingPunct="1"><a:defRPr sz="1800" kern="1200"><a:solidFill><a:schemeClr val="tx1"/></a:solidFill><a:latin typeface="+mn-lt"/><a:ea typeface="+mn-ea"/><a:cs typeface="+mn-cs"/></a:defRPr></a:lvl3pPr><a:lvl4pPr marL="1371600" algn="l" defTabSz="914400" rtl="0" eaLnBrk="1" latinLnBrk="0" hangingPunct="1"><a:defRPr sz="1800" kern="1200"><a:solidFill><a:schemeClr val="tx1"/></a:solidFill><a:latin typeface="+mn-lt"/><a:ea typeface="+mn-ea"/><a:cs typeface="+mn-cs"/></a:defRPr></a:lvl4pPr><a:lvl5pPr marL="1828800" algn="l" defTabSz="914400" rtl="0" eaLnBrk="1" latinLnBrk="0" hangingPunct="1"><a:defRPr sz="1800" kern="1200"><a:solidFill><a:schemeClr val="tx1"/></a:solidFill><a:latin typeface="+mn-lt"/><a:ea typeface="+mn-ea"/><a:cs typeface="+mn-cs"/></a:defRPr></a:lvl5pPr><a:lvl6pPr marL="2286000" algn="l" defTabSz="914400" rtl="0" eaLnBrk="1" latinLnBrk="0" hangingPunct="1"><a:defRPr sz="1800" kern="1200"><a:solidFill><a:schemeClr val="tx1"/></a:solidFill><a:latin typeface="+mn-lt"/><a:ea typeface="+mn-ea"/><a:cs typeface="+mn-cs"/></a:defRPr></a:lvl6pPr><a:lvl7pPr marL="2743200" algn="l" defTabSz="914400" rtl="0" eaLnBrk="1" latinLnBrk="0" hangingPunct="1"><a:defRPr sz="1800" kern="1200"><a:solidFill><a:schemeClr val="tx1"/></a:solidFill><a:latin typeface="+mn-lt"/><a:ea typeface="+mn-ea"/><a:cs typeface="+mn-cs"/></a:defRPr></a:lvl7pPr><a:lvl8pPr marL="3200400" algn="l" defTabSz="914400" rtl="0" eaLnBrk="1" latinLnBrk="0" hangingPunct="1"><a:defRPr sz="1800" kern="1200"><a:solidFill><a:schemeClr val="tx1"/></a:solidFill><a:latin typeface="+mn-lt"/><a:ea typeface="+mn-ea"/><a:cs typeface="+mn-cs"/></a:defRPr></a:lvl8pPr><a:lvl9pPr marL="3657600" algn="l" defTabSz="914400" rtl="0" eaLnBrk="1" latinLnBrk="0" hangingPunct="1"><a:defRPr sz="1800" kern="1200"><a:solidFill><a:schemeClr val="tx1"/></a:solidFill><a:latin typeface="+mn-lt"/><a:ea typeface="+mn-ea"/><a:cs typeface="+mn-cs"/></a:defRPr></a:lvl9pPr></a:lstStyle><a:p><a:pPr algn="ctr"/><a:endParaRPr lang="en-US" sz="900"><a:solidFill><a:srgbClr val="DC2F34"/></a:solidFill><a:latin typeface="돋움" pitchFamily="50" charset="-127"/><a:ea typeface="돋움" pitchFamily="50" charset="-127"/></a:endParaRPr></a:p></p:txBody></p:sp></p:grpSp><p:sp><p:nvSpPr><p:cNvPr id="55" name="TextBox 54"><a:extLst><a:ext uri="{FF2B5EF4-FFF2-40B4-BE49-F238E27FC236}"><a16:creationId xmlns:a16="http://schemas.microsoft.com/office/drawing/2014/main" id="{EFC3480B-B9A0-EF59-3889-7C184E9AFAF5}"/></a:ext></a:extLst></p:cNvPr><p:cNvSpPr txBox="1"/><p:nvPr/></p:nvSpPr><p:spPr><a:xfrm><a:off x="1244588" y="2171299"/><a:ext cx="7380820" cy="213585"/></a:xfrm><a:prstGeom prst="rect"><a:avLst/></a:prstGeom><a:noFill/></p:spPr><p:txBody><a:bodyPr wrap="square" lIns="0" tIns="0" rIns="0" bIns="0" rtlCol="0" anchor="ctr"><a:spAutoFit/></a:bodyPr><a:lstStyle/><a:p><a:pPr algn="ctr"><a:lnSpc><a:spcPct val="130000"/></a:lnSpc></a:pPr><a:r><a:rPr lang="en-US" altLang="ko-KR" sz="1200" dirty="0"><a:solidFill><a:srgbClr val="123E8C"/></a:solidFill><a:latin typeface="맑은 고딕" panose="020B0503020000020004" pitchFamily="50" charset="-127"/><a:ea typeface="맑은 고딕" panose="020B0503020000020004" pitchFamily="50" charset="-127"/></a:rPr><a:t>[ </a:t></a:r><a:r><a:rPr lang="ko-KR" altLang="en-US" sz="1200" dirty="0"><a:solidFill><a:srgbClr val="123E8C"/></a:solidFill><a:latin typeface="맑은 고딕" panose="020B0503020000020004" pitchFamily="50" charset="-127"/><a:ea typeface="맑은 고딕" panose="020B0503020000020004" pitchFamily="50" charset="-127"/></a:rPr><a:t>기본 채널인 </a:t></a:r><a:r><a:rPr lang="en-US" altLang="ko-KR" sz="1200" dirty="0"><a:solidFill><a:srgbClr val="123E8C"/></a:solidFill><a:latin typeface="맑은 고딕" panose="020B0503020000020004" pitchFamily="50" charset="-127"/><a:ea typeface="맑은 고딕" panose="020B0503020000020004" pitchFamily="50" charset="-127"/></a:rPr><a:t>PC </a:t></a:r><a:r><a:rPr lang="ko-KR" altLang="en-US" sz="1200" dirty="0"><a:solidFill><a:srgbClr val="123E8C"/></a:solidFill><a:latin typeface="맑은 고딕" panose="020B0503020000020004" pitchFamily="50" charset="-127"/><a:ea typeface="맑은 고딕" panose="020B0503020000020004" pitchFamily="50" charset="-127"/></a:rPr><a:t>웹사이트를 중심으로 전략적 방향성을 담아낸  </a:t></a:r><a:r><a:rPr lang="en-US" altLang="ko-KR" sz="1200" dirty="0"><a:solidFill><a:srgbClr val="123E8C"/></a:solidFill><a:latin typeface="맑은 고딕" panose="020B0503020000020004" pitchFamily="50" charset="-127"/><a:ea typeface="맑은 고딕" panose="020B0503020000020004" pitchFamily="50" charset="-127"/></a:rPr><a:t>UI</a:t></a:r><a:r><a:rPr lang="ko-KR" altLang="en-US" sz="1200" dirty="0"><a:solidFill><a:srgbClr val="123E8C"/></a:solidFill><a:latin typeface="맑은 고딕" panose="020B0503020000020004" pitchFamily="50" charset="-127"/><a:ea typeface="맑은 고딕" panose="020B0503020000020004" pitchFamily="50" charset="-127"/></a:rPr><a:t> 예시 구성 </a:t></a:r><a:r><a:rPr lang="en-US" altLang="ko-KR" sz="1200" dirty="0"><a:solidFill><a:srgbClr val="123E8C"/></a:solidFill><a:latin typeface="맑은 고딕" panose="020B0503020000020004" pitchFamily="50" charset="-127"/><a:ea typeface="맑은 고딕" panose="020B0503020000020004" pitchFamily="50" charset="-127"/></a:rPr><a:t>]</a:t></a:r><a:r><a:rPr lang="ko-KR" altLang="en-US" sz="1200" dirty="0"><a:solidFill><a:srgbClr val="123E8C"/></a:solidFill><a:latin typeface="맑은 고딕" panose="020B0503020000020004" pitchFamily="50" charset="-127"/><a:ea typeface="맑은 고딕" panose="020B0503020000020004" pitchFamily="50" charset="-127"/></a:rPr><a:t> </a:t></a:r></a:p></p:txBody></p:sp><p:grpSp><p:nvGrpSpPr><p:cNvPr id="26" name="그룹 25"><a:extLst><a:ext uri="{FF2B5EF4-FFF2-40B4-BE49-F238E27FC236}"><a16:creationId xmlns:a16="http://schemas.microsoft.com/office/drawing/2014/main" id="{700A7DB8-7910-6C97-62D2-9F1DFE1A4A23}"/></a:ext></a:extLst></p:cNvPr><p:cNvGrpSpPr/><p:nvPr/></p:nvGrpSpPr><p:grpSpPr><a:xfrm><a:off x="645780" y="2240305"/><a:ext cx="4500500" cy="4500500"/><a:chOff x="645780" y="2168860"/><a:chExt cx="4500500" cy="4500500"/></a:xfrm></p:grpSpPr><p:pic><p:nvPicPr><p:cNvPr id="4" name="그림 3" descr="스크린샷, 블랙, 컴퓨터 모니터, 디자인이(가) 표시된 사진&#xA;&#xA;AI 생성 콘텐츠는 정확하지 않을 수 있습니다."><a:extLst><a:ext uri="{FF2B5EF4-FFF2-40B4-BE49-F238E27FC236}"><a16:creationId xmlns:a16="http://schemas.microsoft.com/office/drawing/2014/main" id="{69D7D9B2-F42B-455B-5352-953040926AF5}"/></a:ext></a:extLst></p:cNvPr><p:cNvPicPr><a:picLocks noChangeAspect="1"/></p:cNvPicPr><p:nvPr/></p:nvPicPr><p:blipFill><a:blip r:embed="rId2"><a:extLst><a:ext uri="{28A0092B-C50C-407E-A947-70E740481C1C}"><a14:useLocalDpi xmlns:a14="http://schemas.microsoft.com/office/drawing/2010/main" val="0"/></a:ext></a:extLst></a:blip><a:stretch><a:fillRect/></a:stretch></p:blipFill><p:spPr><a:xfrm><a:off x="645780" y="2168860"/><a:ext cx="4500500" cy="4500500"/></a:xfrm><a:prstGeom prst="rect"><a:avLst/></a:prstGeom></p:spPr></p:pic><p:pic><p:nvPicPr><p:cNvPr id="18" name="그림 17" descr="텍스트, 스크린샷, 소프트웨어, 번호이(가) 표시된 사진&#xA;&#xA;AI 생성 콘텐츠는 정확하지 않을 수 있습니다."><a:extLst><a:ext uri="{FF2B5EF4-FFF2-40B4-BE49-F238E27FC236}"><a16:creationId xmlns:a16="http://schemas.microsoft.com/office/drawing/2014/main" id="{BB097F4E-C465-0EF9-A4C8-954CEB6C36DC}"/></a:ext></a:extLst></p:cNvPr><p:cNvPicPr><a:picLocks noChangeAspect="1"/></p:cNvPicPr><p:nvPr/></p:nvPicPr><p:blipFill><a:blip r:embed="rId3"><a:extLst><a:ext uri="{BEBA8EAE-BF5A-486C-A8C5-ECC9F3942E4B}"><a14:imgProps xmlns:a14="http://schemas.microsoft.com/office/drawing/2010/main"><a14:imgLayer r:embed="rId4"><a14:imgEffect><a14:saturation sat="0"/></a14:imgEffect></a14:imgLayer></a14:imgProps></a:ext><a:ext uri="{28A0092B-C50C-407E-A947-70E740481C1C}"><a14:useLocalDpi xmlns:a14="http://schemas.microsoft.com/office/drawing/2010/main" val="0"/></a:ext></a:extLst></a:blip><a:stretch><a:fillRect/></a:stretch></p:blipFill><p:spPr><a:xfrm><a:off x="1784648" y="3136613"/><a:ext cx="2196244" cy="1908212"/></a:xfrm><a:prstGeom prst="rect"><a:avLst/></a:prstGeom><a:ln w="3175"><a:solidFill><a:schemeClr val="bg1"><a:lumMod val="50000"/></a:schemeClr></a:solidFill></a:ln></p:spPr></p:pic><p:sp><p:nvSpPr><p:cNvPr id="20" name="직사각형 19"><a:extLst><a:ext uri="{FF2B5EF4-FFF2-40B4-BE49-F238E27FC236}"><a16:creationId xmlns:a16="http://schemas.microsoft.com/office/drawing/2014/main" id="{7DCDFE3E-22EF-2882-C142-732A22294D48}"/></a:ext></a:extLst></p:cNvPr><p:cNvSpPr/><p:nvPr/></p:nvSpPr><p:spPr><a:xfrm><a:off x="2740817" y="2719179"/><a:ext cx="713275" cy="230832"/></a:xfrm><a:prstGeom prst="rect"><a:avLst/></a:prstGeom></p:spPr><p:txBody><a:bodyPr wrap="square"><a:spAutoFit/></a:bodyPr><a:lstStyle/><a:p><a:r><a:rPr lang="en-US" altLang="ko-Kore-KR" sz="900" b="1" dirty="0"><a:solidFill><a:srgbClr val="E50019"/></a:solidFill><a:latin typeface="맑은 고딕" panose="020B0503020000020004" pitchFamily="50" charset="-127"/><a:ea typeface="맑은 고딕" panose="020B0503020000020004" pitchFamily="50" charset="-127"/></a:rPr><a:t>Complex</a:t></a:r><a:endParaRPr lang="ko-Kore-KR" altLang="en-US" sz="900" b="1" dirty="0"><a:solidFill><a:srgbClr val="E50019"/></a:solidFill><a:latin typeface="맑은 고딕" panose="020B0503020000020004" pitchFamily="50" charset="-127"/><a:ea typeface="맑은 고딕" panose="020B0503020000020004" pitchFamily="50" charset="-127"/></a:endParaRPr></a:p></p:txBody></p:sp><p:sp><p:nvSpPr><p:cNvPr id="23" name="모서리가 둥근 직사각형 94"><a:extLst><a:ext uri="{FF2B5EF4-FFF2-40B4-BE49-F238E27FC236}"><a16:creationId xmlns:a16="http://schemas.microsoft.com/office/drawing/2014/main" id="{BE780903-3887-AD16-8719-89C56DBCA7C8}"/></a:ext></a:extLst></p:cNvPr><p:cNvSpPr/><p:nvPr/></p:nvSpPr><p:spPr><a:xfrm><a:off x="2289610" y="2733382"/><a:ext cx="472014" cy="189463"/></a:xfrm><a:prstGeom prst="roundRect"><a:avLst><a:gd name="adj" fmla="val 50000"/></a:avLst></a:prstGeom><a:solidFill><a:schemeClr val="tx1"><a:lumMod val="85000"/><a:lumOff val="15000"/></a:schemeClr></a:solidFill><a:ln w="6350"><a:solidFill><a:schemeClr val="tx1"><a:lumMod val="75000"/><a:lumOff val="25000"/></a:schemeClr></a:solidFill></a:ln></p:spPr><p:style><a:lnRef idx="2"><a:schemeClr val="accent1"><a:shade val="50000"/></a:schemeClr></a:lnRef><a:fillRef idx="1"><a:schemeClr val="accent1"/></a:fillRef><a:effectRef idx="0"><a:schemeClr val="accent1"/></a:effectRef><a:fontRef idx="minor"><a:schemeClr val="lt1"/></a:fontRef></p:style><p:txBody><a:bodyPr lIns="0" tIns="0" rIns="0" bIns="0" rtlCol="0" anchor="ctr"/><a:lstStyle/><a:p><a:pPr algn="ctr"/><a:r><a:rPr kumimoji="1" lang="en-US" altLang="ko-Kore-KR" sz="800" dirty="0"><a:solidFill><a:schemeClr val="bg1"/></a:solidFill><a:latin typeface="맑은 고딕" panose="020B0503020000020004" pitchFamily="50" charset="-127"/><a:ea typeface="맑은 고딕" panose="020B0503020000020004" pitchFamily="50" charset="-127"/></a:rPr><a:t>Home</a:t></a:r><a:endParaRPr kumimoji="1" lang="ko-Kore-KR" altLang="en-US" sz="800" dirty="0"><a:solidFill><a:schemeClr val="bg1"/></a:solidFill><a:latin typeface="맑은 고딕" panose="020B0503020000020004" pitchFamily="50" charset="-127"/><a:ea typeface="맑은 고딕" panose="020B0503020000020004" pitchFamily="50" charset="-127"/></a:endParaRPr></a:p></p:txBody></p:sp></p:grpSp><p:grpSp><p:nvGrpSpPr><p:cNvPr id="27" name="그룹 26"><a:extLst><a:ext uri="{FF2B5EF4-FFF2-40B4-BE49-F238E27FC236}"><a16:creationId xmlns:a16="http://schemas.microsoft.com/office/drawing/2014/main" id="{E64DC5A0-1A1C-13C3-827C-A5A16A414728}"/></a:ext></a:extLst></p:cNvPr><p:cNvGrpSpPr/><p:nvPr/></p:nvGrpSpPr><p:grpSpPr><a:xfrm><a:off x="4664968" y="2240305"/><a:ext cx="4500500" cy="4500500"/><a:chOff x="4664968" y="2059494"/><a:chExt cx="4500500" cy="4500500"/></a:xfrm></p:grpSpPr><p:pic><p:nvPicPr><p:cNvPr id="10" name="그림 9" descr="스크린샷, 블랙, 컴퓨터 모니터, 디자인이(가) 표시된 사진&#xA;&#xA;AI 생성 콘텐츠는 정확하지 않을 수 있습니다."><a:extLst><a:ext uri="{FF2B5EF4-FFF2-40B4-BE49-F238E27FC236}"><a16:creationId xmlns:a16="http://schemas.microsoft.com/office/drawing/2014/main" id="{FD2AD687-FFFF-4C76-77CA-8ACD86A246FF}"/></a:ext></a:extLst></p:cNvPr><p:cNvPicPr><a:picLocks noChangeAspect="1"/></p:cNvPicPr><p:nvPr/></p:nvPicPr><p:blipFill><a:blip r:embed="rId2"><a:extLst><a:ext uri="{28A0092B-C50C-407E-A947-70E740481C1C}"><a14:useLocalDpi xmlns:a14="http://schemas.microsoft.com/office/drawing/2010/main" val="0"/></a:ext></a:extLst></a:blip><a:stretch><a:fillRect/></a:stretch></p:blipFill><p:spPr><a:xfrm><a:off x="4664968" y="2059494"/><a:ext cx="4500500" cy="4500500"/></a:xfrm><a:prstGeom prst="rect"><a:avLst/></a:prstGeom></p:spPr></p:pic><p:pic><p:nvPicPr><p:cNvPr id="14" name="그림 13" descr="텍스트, 스크린샷, 번호, 폰트이(가) 표시된 사진&#xA;&#xA;AI 생성 콘텐츠는 정확하지 않을 수 있습니다."><a:extLst><a:ext uri="{FF2B5EF4-FFF2-40B4-BE49-F238E27FC236}"><a16:creationId xmlns:a16="http://schemas.microsoft.com/office/drawing/2014/main" id="{C426EDC8-84A7-E296-A088-706D106CDCC4}"/></a:ext></a:extLst></p:cNvPr><p:cNvPicPr><a:picLocks noChangeAspect="1"/></p:cNvPicPr><p:nvPr/></p:nvPicPr><p:blipFill><a:blip r:embed="rId5"><a:extLst><a:ext uri="{BEBA8EAE-BF5A-486C-A8C5-ECC9F3942E4B}"><a14:imgProps xmlns:a14="http://schemas.microsoft.com/office/drawing/2010/main"><a14:imgLayer r:embed="rId6"><a14:imgEffect><a14:saturation sat="0"/></a14:imgEffect></a14:imgLayer></a14:imgProps></a:ext><a:ext uri="{28A0092B-C50C-407E-A947-70E740481C1C}"><a14:useLocalDpi xmlns:a14="http://schemas.microsoft.com/office/drawing/2010/main" val="0"/></a:ext></a:extLst></a:blip><a:stretch><a:fillRect/></a:stretch></p:blipFill><p:spPr><a:xfrm><a:off x="5709084" y="3032956"/><a:ext cx="2431113" cy="1908212"/></a:xfrm><a:prstGeom prst="rect"><a:avLst/></a:prstGeom><a:ln w="3175"><a:solidFill><a:schemeClr val="bg1"><a:lumMod val="50000"/></a:schemeClr></a:solidFill></a:ln></p:spPr></p:pic><p:sp><p:nvSpPr><p:cNvPr id="22" name="직사각형 21"><a:extLst><a:ext uri="{FF2B5EF4-FFF2-40B4-BE49-F238E27FC236}"><a16:creationId xmlns:a16="http://schemas.microsoft.com/office/drawing/2014/main" id="{479BF396-2B4D-3243-CA46-EE24257F4647}"/></a:ext></a:extLst></p:cNvPr><p:cNvSpPr/><p:nvPr/></p:nvSpPr><p:spPr><a:xfrm><a:off x="6540226" y="2622104"/><a:ext cx="1234346" cy="230832"/></a:xfrm><a:prstGeom prst="rect"><a:avLst/></a:prstGeom></p:spPr><p:txBody><a:bodyPr wrap="square"><a:spAutoFit/></a:bodyPr><a:lstStyle/><a:p><a:pPr algn="ctr"/><a:r><a:rPr lang="en-US" altLang="ko-Kore-KR" sz="900" b="1" dirty="0"><a:solidFill><a:srgbClr val="E50019"/></a:solidFill><a:latin typeface="맑은 고딕" panose="020B0503020000020004" pitchFamily="50" charset="-127"/><a:ea typeface="맑은 고딕" panose="020B0503020000020004" pitchFamily="50" charset="-127"/></a:rPr><a:t>Tap ▪︎ Scroll</a:t></a:r><a:endParaRPr lang="ko-Kore-KR" altLang="en-US" sz="900" b="1" dirty="0"><a:solidFill><a:srgbClr val="E50019"/></a:solidFill><a:latin typeface="맑은 고딕" panose="020B0503020000020004" pitchFamily="50" charset="-127"/><a:ea typeface="맑은 고딕" panose="020B0503020000020004" pitchFamily="50" charset="-127"/></a:endParaRPr></a:p></p:txBody></p:sp><p:sp><p:nvSpPr><p:cNvPr id="25" name="모서리가 둥근 직사각형 96"><a:extLst><a:ext uri="{FF2B5EF4-FFF2-40B4-BE49-F238E27FC236}"><a16:creationId xmlns:a16="http://schemas.microsoft.com/office/drawing/2014/main" id="{C1D04CE9-1F1F-63ED-A330-75FEB52827CE}"/></a:ext></a:extLst></p:cNvPr><p:cNvSpPr/><p:nvPr/></p:nvSpPr><p:spPr><a:xfrm><a:off x="6255459" y="2629724"/><a:ext cx="472014" cy="189463"/></a:xfrm><a:prstGeom prst="roundRect"><a:avLst><a:gd name="adj" fmla="val 50000"/></a:avLst></a:prstGeom><a:solidFill><a:schemeClr val="tx1"><a:lumMod val="85000"/><a:lumOff val="15000"/></a:schemeClr></a:solidFill><a:ln w="6350"><a:solidFill><a:schemeClr val="tx1"><a:lumMod val="75000"/><a:lumOff val="25000"/></a:schemeClr></a:solidFill></a:ln></p:spPr><p:style><a:lnRef idx="2"><a:schemeClr val="accent1"><a:shade val="50000"/></a:schemeClr></a:lnRef><a:fillRef idx="1"><a:schemeClr val="accent1"/></a:fillRef><a:effectRef idx="0"><a:schemeClr val="accent1"/></a:effectRef><a:fontRef idx="minor"><a:schemeClr val="lt1"/></a:fontRef></p:style><p:txBody><a:bodyPr lIns="0" tIns="0" rIns="0" bIns="0" rtlCol="0" anchor="ctr"/><a:lstStyle/><a:p><a:pPr algn="ctr"/><a:r><a:rPr kumimoji="1" lang="en-US" altLang="ko-Kore-KR" sz="800" dirty="0"><a:solidFill><a:schemeClr val="bg1"/></a:solidFill><a:latin typeface="맑은 고딕" panose="020B0503020000020004" pitchFamily="50" charset="-127"/><a:ea typeface="맑은 고딕" panose="020B0503020000020004" pitchFamily="50" charset="-127"/></a:rPr><a:t>Detail</a:t></a:r><a:endParaRPr kumimoji="1" lang="ko-Kore-KR" altLang="en-US" sz="800" dirty="0"><a:solidFill><a:schemeClr val="bg1"/></a:solidFill><a:latin typeface="맑은 고딕" panose="020B0503020000020004" pitchFamily="50" charset="-127"/><a:ea typeface="맑은 고딕" panose="020B0503020000020004" pitchFamily="50" charset="-127"/></a:endParaRPr></a:p></p:txBody></p:sp></p:grpSp><p:sp><p:nvSpPr><p:cNvPr id="43" name="아래쪽 화살표[D] 53"><a:extLst><a:ext uri="{FF2B5EF4-FFF2-40B4-BE49-F238E27FC236}"><a16:creationId xmlns:a16="http://schemas.microsoft.com/office/drawing/2014/main" id="{122A6C1F-4DB1-3608-366B-BBB02F6BD14D}"/></a:ext></a:extLst></p:cNvPr><p:cNvSpPr/><p:nvPr/></p:nvSpPr><p:spPr><a:xfrm rot="5400000" flipH="1" flipV="1"><a:off x="2454148" y="2767775"/><a:ext cx="286355" cy="1470988"/></a:xfrm><a:prstGeom prst="downArrow"><a:avLst/></a:prstGeom><a:solidFill><a:srgbClr val="FF7E79"><a:alpha val="49412"/></a:srgbClr></a:solidFill><a:ln><a:noFill/></a:ln></p:spPr><p:style><a:lnRef idx="2"><a:schemeClr val="accent1"><a:shade val="50000"/></a:schemeClr></a:lnRef><a:fillRef idx="1"><a:schemeClr val="accent1"/></a:fillRef><a:effectRef idx="0"><a:schemeClr val="accent1"/></a:effectRef><a:fontRef idx="minor"><a:schemeClr val="lt1"/></a:fontRef></p:style><p:txBody><a:bodyPr rtlCol="0" anchor="ctr"/><a:lstStyle/><a:p><a:pPr algn="ctr"/><a:endParaRPr kumimoji="1" lang="ko-Kore-KR" altLang="en-US" dirty="0"><a:latin typeface="맑은 고딕" panose="020B0503020000020004" pitchFamily="50" charset="-127"/><a:ea typeface="맑은 고딕" panose="020B0503020000020004" pitchFamily="50" charset="-127"/></a:endParaRPr></a:p></p:txBody></p:sp><p:sp><p:nvSpPr><p:cNvPr id="44" name="아래쪽 화살표[D] 52"><a:extLst><a:ext uri="{FF2B5EF4-FFF2-40B4-BE49-F238E27FC236}"><a16:creationId xmlns:a16="http://schemas.microsoft.com/office/drawing/2014/main" id="{59D53AC0-E888-C4DA-B26D-C708DB27ED6D}"/></a:ext></a:extLst></p:cNvPr><p:cNvSpPr/><p:nvPr/></p:nvSpPr><p:spPr><a:xfrm rot="10800000" flipH="1" flipV="1"><a:off x="6525489" y="4529641"/><a:ext cx="389729" cy="586629"/></a:xfrm><a:prstGeom prst="downArrow"><a:avLst/></a:prstGeom><a:solidFill><a:srgbClr val="FF7E79"><a:alpha val="49412"/></a:srgbClr></a:solidFill><a:ln><a:noFill/></a:ln></p:spPr><p:style><a:lnRef idx="2"><a:schemeClr val="accent1"><a:shade val="50000"/></a:schemeClr></a:lnRef><a:fillRef idx="1"><a:schemeClr val="accent1"/></a:fillRef><a:effectRef idx="0"><a:schemeClr val="accent1"/></a:effectRef><a:fontRef idx="minor"><a:schemeClr val="lt1"/></a:fontRef></p:style><p:txBody><a:bodyPr rtlCol="0" anchor="ctr"/><a:lstStyle/><a:p><a:pPr algn="ctr"/><a:endParaRPr kumimoji="1" lang="ko-Kore-KR" altLang="en-US" dirty="0"><a:latin typeface="맑은 고딕" panose="020B0503020000020004" pitchFamily="50" charset="-127"/><a:ea typeface="맑은 고딕" panose="020B0503020000020004" pitchFamily="50" charset="-127"/></a:endParaRPr></a:p></p:txBody></p:sp><p:sp><p:nvSpPr><p:cNvPr id="45" name="아래쪽 화살표[D] 52"><a:extLst><a:ext uri="{FF2B5EF4-FFF2-40B4-BE49-F238E27FC236}"><a16:creationId xmlns:a16="http://schemas.microsoft.com/office/drawing/2014/main" id="{252BFDD0-6FCA-AD44-17B5-D4CC64546B90}"/></a:ext></a:extLst></p:cNvPr><p:cNvSpPr/><p:nvPr/></p:nvSpPr><p:spPr><a:xfrm rot="10800000" flipH="1" flipV="1"><a:off x="2624681" y="4506178"/><a:ext cx="389729" cy="586629"/></a:xfrm><a:prstGeom prst="downArrow"><a:avLst/></a:prstGeom><a:solidFill><a:srgbClr val="FF7E79"><a:alpha val="49412"/></a:srgbClr></a:solidFill><a:ln><a:noFill/></a:ln></p:spPr><p:style><a:lnRef idx="2"><a:schemeClr val="accent1"><a:shade val="50000"/></a:schemeClr></a:lnRef><a:fillRef idx="1"><a:schemeClr val="accent1"/></a:fillRef><a:effectRef idx="0"><a:schemeClr val="accent1"/></a:effectRef><a:fontRef idx="minor"><a:schemeClr val="lt1"/></a:fontRef></p:style><p:txBody><a:bodyPr rtlCol="0" anchor="ctr"/><a:lstStyle/><a:p><a:pPr algn="ctr"/><a:endParaRPr kumimoji="1" lang="ko-Kore-KR" altLang="en-US" dirty="0"><a:latin typeface="맑은 고딕" panose="020B0503020000020004" pitchFamily="50" charset="-127"/><a:ea typeface="맑은 고딕" panose="020B0503020000020004" pitchFamily="50" charset="-127"/></a:endParaRPr></a:p></p:txBody></p:sp><p:sp><p:nvSpPr><p:cNvPr id="46" name="아래쪽 화살표[D] 53"><a:extLst><a:ext uri="{FF2B5EF4-FFF2-40B4-BE49-F238E27FC236}"><a16:creationId xmlns:a16="http://schemas.microsoft.com/office/drawing/2014/main" id="{D3E2C561-8840-A8EB-B80D-1B5A26234305}"/></a:ext></a:extLst></p:cNvPr><p:cNvSpPr/><p:nvPr/></p:nvSpPr><p:spPr><a:xfrm rot="5400000" flipH="1" flipV="1"><a:off x="6412001" y="2752176"/><a:ext cx="286355" cy="1692189"/></a:xfrm><a:prstGeom prst="downArrow"><a:avLst/></a:prstGeom><a:solidFill><a:srgbClr val="FF7E79"><a:alpha val="49412"/></a:srgbClr></a:solidFill><a:ln><a:noFill/></a:ln></p:spPr><p:style><a:lnRef idx="2"><a:schemeClr val="accent1"><a:shade val="50000"/></a:schemeClr></a:lnRef><a:fillRef idx="1"><a:schemeClr val="accent1"/></a:fillRef><a:effectRef idx="0"><a:schemeClr val="accent1"/></a:effectRef><a:fontRef idx="minor"><a:schemeClr val="lt1"/></a:fontRef></p:style><p:txBody><a:bodyPr rtlCol="0" anchor="ctr"/><a:lstStyle/><a:p><a:pPr algn="ctr"/><a:endParaRPr kumimoji="1" lang="ko-Kore-KR" altLang="en-US" dirty="0"><a:latin typeface="맑은 고딕" panose="020B0503020000020004" pitchFamily="50" charset="-127"/><a:ea typeface="맑은 고딕" panose="020B0503020000020004" pitchFamily="50" charset="-127"/></a:endParaRPr></a:p></p:txBody></p:sp><p:cxnSp><p:nvCxnSpPr><p:cNvPr id="47" name="연결선: 꺾임 46"><a:extLst><a:ext uri="{FF2B5EF4-FFF2-40B4-BE49-F238E27FC236}"><a16:creationId xmlns:a16="http://schemas.microsoft.com/office/drawing/2014/main" id="{CF20A3C5-40E7-E8B9-D484-9FA347070705}"/></a:ext></a:extLst></p:cNvPr><p:cNvCxnSpPr><a:cxnSpLocks/></p:cNvCxnSpPr><p:nvPr/></p:nvCxnSpPr><p:spPr><a:xfrm flipV="1"><a:off x="3846474" y="4220525"/><a:ext cx="1345294" cy="566051"/></a:xfrm><a:prstGeom prst="bentConnector3"><a:avLst><a:gd name="adj1" fmla="val 76118"/></a:avLst></a:prstGeom><a:ln><a:solidFill><a:srgbClr val="123E8C"/></a:solidFill><a:prstDash val="sysDot"/><a:tailEnd type="triangle"/></a:ln></p:spPr><p:style><a:lnRef idx="2"><a:schemeClr val="accent1"/></a:lnRef><a:fillRef idx="0"><a:schemeClr val="accent1"/></a:fillRef><a:effectRef idx="1"><a:schemeClr val="accent1"/></a:effectRef><a:fontRef idx="minor"><a:schemeClr val="tx1"/></a:fontRef></p:style></p:cxnSp><p:sp><p:nvSpPr><p:cNvPr id="11" name="직사각형 10"><a:extLst><a:ext uri="{FF2B5EF4-FFF2-40B4-BE49-F238E27FC236}"><a16:creationId xmlns:a16="http://schemas.microsoft.com/office/drawing/2014/main" id="{2231ED43-4372-CAA3-01E3-CA599DBF876D}"/></a:ext></a:extLst></p:cNvPr><p:cNvSpPr/><p:nvPr/></p:nvSpPr><p:spPr><a:xfrm><a:off x="272480" y="1206820"/><a:ext cx="9433048" cy="477722"/></a:xfrm><a:prstGeom prst="rect"><a:avLst/></a:prstGeom><a:noFill/><a:ln><a:noFill/></a:ln></p:spPr><p:style><a:lnRef idx="2"><a:schemeClr val="accent1"><a:shade val="15000"/></a:schemeClr></a:lnRef><a:fillRef idx="1"><a:schemeClr val="accent1"/></a:fillRef><a:effectRef idx="0"><a:schemeClr val="accent1"/></a:effectRef><a:fontRef idx="minor"><a:schemeClr val="lt1"/></a:fontRef></p:style><p:txBody><a:bodyPr rtlCol="0" anchor="ctr"/><a:lstStyle/><a:p><a:r><a:rPr lang="ko-KR" altLang="en-US" sz="1100" dirty="0"><a:solidFill><a:schemeClr val="tx1"/></a:solidFill><a:latin typeface="+mn-ea"/><a:cs typeface="Malgun Gothic Semilight" panose="020B0502040204020203" pitchFamily="50" charset="-127"/><a:sym typeface="Wingdings" panose="05000000000000000000" pitchFamily="2" charset="2"/></a:rPr><a:t>사용자를 중심으로 보다 </a:t></a:r><a:r><a:rPr lang="ko-KR" altLang="en-US" sz="1100" b="1" dirty="0"><a:solidFill><a:schemeClr val="tx1"/></a:solidFill><a:latin typeface="+mn-ea"/><a:cs typeface="Malgun Gothic Semilight" panose="020B0502040204020203" pitchFamily="50" charset="-127"/><a:sym typeface="Wingdings" panose="05000000000000000000" pitchFamily="2" charset="2"/></a:rPr><a:t>쉽고</a:t></a:r><a:r><a:rPr lang="en-US" altLang="ko-KR" sz="1100" b="1" dirty="0"><a:solidFill><a:schemeClr val="tx1"/></a:solidFill><a:latin typeface="+mn-ea"/><a:cs typeface="Malgun Gothic Semilight" panose="020B0502040204020203" pitchFamily="50" charset="-127"/><a:sym typeface="Wingdings" panose="05000000000000000000" pitchFamily="2" charset="2"/></a:rPr><a:t>, </a:t></a:r><a:r><a:rPr lang="ko-KR" altLang="en-US" sz="1100" b="1" dirty="0"><a:solidFill><a:schemeClr val="tx1"/></a:solidFill><a:latin typeface="+mn-ea"/><a:cs typeface="Malgun Gothic Semilight" panose="020B0502040204020203" pitchFamily="50" charset="-127"/><a:sym typeface="Wingdings" panose="05000000000000000000" pitchFamily="2" charset="2"/></a:rPr><a:t>빠르고</a:t></a:r><a:r><a:rPr lang="en-US" altLang="ko-KR" sz="1100" b="1" dirty="0"><a:solidFill><a:schemeClr val="tx1"/></a:solidFill><a:latin typeface="+mn-ea"/><a:cs typeface="Malgun Gothic Semilight" panose="020B0502040204020203" pitchFamily="50" charset="-127"/><a:sym typeface="Wingdings" panose="05000000000000000000" pitchFamily="2" charset="2"/></a:rPr><a:t>, </a:t></a:r><a:r><a:rPr lang="ko-KR" altLang="en-US" sz="1100" b="1" dirty="0"><a:solidFill><a:schemeClr val="tx1"/></a:solidFill><a:latin typeface="+mn-ea"/><a:cs typeface="Malgun Gothic Semilight" panose="020B0502040204020203" pitchFamily="50" charset="-127"/><a:sym typeface="Wingdings" panose="05000000000000000000" pitchFamily="2" charset="2"/></a:rPr><a:t>편리한 온라인 쇼핑이 가능하도록 </a:t></a:r><a:r><a:rPr lang="en-US" altLang="ko-KR" sz="1100" b="1" dirty="0"><a:solidFill><a:schemeClr val="tx1"/></a:solidFill><a:latin typeface="+mn-ea"/><a:cs typeface="Malgun Gothic Semilight" panose="020B0502040204020203" pitchFamily="50" charset="-127"/><a:sym typeface="Wingdings" panose="05000000000000000000" pitchFamily="2" charset="2"/></a:rPr><a:t>UI</a:t></a:r><a:r><a:rPr lang="ko-KR" altLang="en-US" sz="1100" dirty="0"><a:solidFill><a:schemeClr val="tx1"/></a:solidFill><a:latin typeface="+mn-ea"/><a:cs typeface="Malgun Gothic Semilight" panose="020B0502040204020203" pitchFamily="50" charset="-127"/><a:sym typeface="Wingdings" panose="05000000000000000000" pitchFamily="2" charset="2"/></a:rPr><a:t>를 구현합니다</a:t></a:r><a:r><a:rPr lang="en-US" altLang="ko-KR" sz="1100" dirty="0"><a:solidFill><a:schemeClr val="tx1"/></a:solidFill><a:latin typeface="+mn-ea"/><a:cs typeface="Malgun Gothic Semilight" panose="020B0502040204020203" pitchFamily="50" charset="-127"/><a:sym typeface="Wingdings" panose="05000000000000000000" pitchFamily="2" charset="2"/></a:rPr><a:t>. </a:t></a:r></a:p></p:txBody></p:sp></p:spTree><p:extLst><p:ext uri="{BB962C8B-B14F-4D97-AF65-F5344CB8AC3E}"><p14:creationId xmlns:p14="http://schemas.microsoft.com/office/powerpoint/2010/main" val="3340295271"/></p:ext></p:extLst></p:cSld><p:clrMapOvr><a:masterClrMapping/></p:clrMapOvr></p:sld>